MANIFEST.in
setup.py
anthill/__init__.py
anthill/exec/__init__.py
anthill/exec/admin.py
anthill/exec/handler.py
anthill/exec/options.py
anthill/exec/server.py
anthill/exec/model/__init__.py
anthill/exec/model/api.py
anthill/exec/model/build.py
anthill/exec/model/session.py
anthill/exec/model/sources.py
anthill/exec/model/stdlib.py
anthill/exec/model/util.py
anthill/exec/sql/exec_application_settings.sql
anthill/exec/sql/exec_application_versions.sql
anthill/exec/sql/exec_server.sql
anthill/exec/tests/__init__.py
anthill/exec/tests/test_acceptance.py
anthill/exec/tests/test_functions.py
anthill_exec.egg-info/PKG-INFO
anthill_exec.egg-info/SOURCES.txt
anthill_exec.egg-info/dependency_links.txt
anthill_exec.egg-info/namespace_packages.txt
anthill_exec.egg-info/not-zip-safe
anthill_exec.egg-info/requires.txt
anthill_exec.egg-info/top_level.txt