Metadata-Version: 1.0
Name: anthill-exec
Version: 0.2
Summary: Server-side javascript code execution for Anthill platform
Home-page: https://github.com/anthill-platform/anthill-exec
Author: desertkun
Author-email: desertkun@gmail.com
License: MIT
Platform: UNKNOWN
